privateprefs/__about__.py
privateprefs/__init__.py
privateprefs/privateprefs.py
privateprefs/core/__init__.py
privateprefs/core/cli.py
privateprefs/core/database.py
privateprefs-0.5.1.dist-info/METADATA
privateprefs-0.5.1.dist-info/WHEEL
privateprefs-0.5.1.dist-info/entry_points.txt
privateprefs-0.5.1.dist-info/licenses/LICENSE
privateprefs-0.5.1.dist-info/RECORD
