Metadata-Version: 2.1
Name: privateprefs
Version: 0.5.1
Project-URL: Documentation, https://github.com/DarrenHaba/privateprefs#readme
Project-URL: Issues, https://github.com/DarrenHaba/privateprefs/issues
Project-URL: Source, https://github.com/DarrenHaba/privateprefs
Author-email: Darren Haba <darren@rorep.com>
License-File: LICENSE
Classifier: Development Status :: 4 - Beta
Classifier: Programming Language :: Python
Classifier: Programming Language :: Python :: 3.7
Classifier: Programming Language :: Python :: 3.8
Classifier: Programming Language :: Python :: 3.9
Classifier: Programming Language :: Python :: 3.10
Classifier: Programming Language :: Python :: 3.11
Classifier: Programming Language :: Python :: Implementation :: CPython
Classifier: Programming Language :: Python :: Implementation :: PyPy
Requires-Python: >=3.7
Requires-Dist: platformdirs
